.DS_Store
tests/__init__.py
tests/utils/__init__.py
tests/utils/utils_test.py
upyog/__init__.py
upyog/all.py
upyog/cli.py
upyog/imports.py
upyog/nb2script.py
upyog/ann/__init__.py
upyog/ann/annoy.py
upyog/ann/query_runner.py
upyog/image/_Inter-Light.ttf
upyog/image/__init__.py
upyog/image/cli.py
upyog/image/composition.py
upyog/image/draw.py
upyog/image/img_downloader.py
upyog/image/io.py
upyog/image/pil_operators.py
upyog/image/utils.py
upyog/image/visualiser.py
upyog/ml/__init__.py
upyog/ml/activations.py
upyog/ml/compare_vectors.py
upyog/ml/coreml_utils.py
upyog/ml/eval_dataset.py
upyog/ml/imagenet_utils.py
upyog/ml/imports.py
upyog/ml/model_utils.py
upyog/ml/preprocessing.py
upyog/ml/umap.py
upyog/ml/utils.py
upyog/ml/visualise.py
upyog/os/__init__.py
upyog/os/cli.py
upyog/os/extract_tar_archive.py
upyog/os/patch_pathlib.py
upyog/os/read_files.py
upyog/os/utils.py
upyog/utils/__init__.py
upyog/utils/boxes.py
upyog/utils/date_utils.py
upyog/utils/dict.py
upyog/utils/download.py
upyog/utils/prettify_df.py
upyog/utils/utils.py
upyog/utils/zip_utils.py
upyog-0.7.15.dist-info/METADATA
upyog-0.7.15.dist-info/WHEEL
upyog-0.7.15.dist-info/entry_points.txt
upyog-0.7.15.dist-info/top_level.txt
upyog-0.7.15.dist-info/RECORD
