Metadata-Version: 2.4
Name: upyog
Version: 0.7.15
Summary: Myriad Utilities
Author: Rahul Somani
Author-email: rsomani95@gmail.com
License: MIT
Keywords: utilities
Classifier: Development Status :: 4 - Beta
Classifier: Natural Language :: English
Classifier: Intended Audience :: Developers
Classifier: Programming Language :: Python :: 3.7
Classifier: Programming Language :: Python :: 3.8
Requires-Python: <4,>=3.7
Requires-Dist: fastcore==1.5.33
Requires-Dist: rich
Requires-Dist: numpy
Requires-Dist: pandas
Requires-Dist: pyarrow
Requires-Dist: pyperclip
Requires-Dist: matplotlib
Requires-Dist: loguru
Requires-Dist: aggdraw
Requires-Dist: typing_extensions
Requires-Dist: exif
Requires-Dist: tabulate
Requires-Dist: pytz
Requires-Dist: seaborn
Requires-Dist: tqdm
Provides-Extra: all
Provides-Extra: dev
Requires-Dist: black<21,>=20.8b1; extra == "dev"
Requires-Dist: pytest<7,>=6; extra == "dev"
Requires-Dist: jupyter<2,>=1.0.0; extra == "dev"
Requires-Dist: pre-commit<3,>=2.8.2; extra == "dev"
